raven_fluentd/__init__.py
raven_fluentd/transport/__init__.py
raven_fluentd/transport/fluentd.py
raven_fluentd-0.1.2.dist-info/DESCRIPTION.rst
raven_fluentd-0.1.2.dist-info/METADATA
raven_fluentd-0.1.2.dist-info/RECORD
raven_fluentd-0.1.2.dist-info/WHEEL
raven_fluentd-0.1.2.dist-info/metadata.json
raven_fluentd-0.1.2.dist-info/top_level.txt
