Metadata-Version: 2.0
Name: raven-fluentd
Version: 0.1.2
Summary: A transport for raven-python which supports fluentd.
Home-page: https://github.com/ayemos/raven-transports-fluentd-python
Author: Yuichiro Someya
Author-email: me@ayemos.me
License: MIT license
Keywords: raven fluentd
Platform: UNKNOWN
Classifier: Development Status :: 2 - Pre-Alpha
Classifier: Intended Audience :: Developers
Classifier: License :: OSI Approved :: MIT License
Classifier: Natural Language :: English
Classifier: Programming Language :: Python :: 2
Classifier: Programming Language :: Python :: 2.6
Classifier: Programming Language :: Python :: 2.7
Classifier: Programming Language :: Python :: 3
Classifier: Programming Language :: Python :: 3.3
Classifier: Programming Language :: Python :: 3.4
Classifier: Programming Language :: Python :: 3.5
Requires-Dist: fluent-logger (>=0.5.3)
Requires-Dist: raven (>=6.1.0)
Requires-Dist: six (>=1.10.0)
